skingrabber/__init__.py
skingrabber/skin.py
skingrabber-0.1.6.dist-info/LICENSE
skingrabber-0.1.6.dist-info/METADATA
skingrabber-0.1.6.dist-info/WHEEL
skingrabber-0.1.6.dist-info/top_level.txt
skingrabber-0.1.6.dist-info/RECORD
