Metadata-Version: 2.1
Name: skingrabber
Version: 0.1.6
Summary: A Python 3 wrapper for the Minecraft Skin API
Home-page: https://github.com/MakufonSkifto/skingrabber
Author: MakufonSkifto
Author-email: emirsurmen@gmail.com
License: MIT
Platform: UNKNOWN
Classifier: Programming Language :: Python :: 3
Classifier: License :: OSI Approved :: MIT License
Requires-Python: >=3.6
Requires-Dist: requests
